explorer/__init__.py
explorer/base.py
explorer/py.typed
explorer/univariate.py
explorer/visual.py
d8a_explorer-0.0.1.dist-info/WHEEL
d8a_explorer-0.0.1.dist-info/METADATA
d8a_explorer-0.0.1.dist-info/RECORD
