Metadata-Version: 2.1
Name: d8a-explorer
Version: 0.0.1
Summary: Exploratory Data Analysis Framework
Home-page: https://john-james-ai.github.io/explorer
License: MIT
Author: John James
Author-email: john.james.ai.studio@gmail.com
Requires-Python: >=3.7.1,<4.0
Classifier: Development Status :: 4 - Beta
Classifier: Intended Audience :: Developers
Classifier: License :: OSI Approved :: MIT License
Classifier: Operating System :: OS Independent
Classifier: Programming Language :: Python
Classifier: Programming Language :: Python :: 3
Classifier: Programming Language :: Python :: 3.10
Classifier: Programming Language :: Python :: 3.7
Classifier: Programming Language :: Python :: 3.8
Classifier: Programming Language :: Python :: 3.9
Classifier: Topic :: Software Development :: Libraries :: Python Modules
Classifier: Typing :: Typed
Project-URL: Documentation, https://john-james-ai.github.io/explorer
Project-URL: Repository, https://github.com/john-james-ai/explorer
